markdown_pycon-1.0.1.dist-info/METADATA
markdown_pycon-1.0.1.dist-info/WHEEL
markdown_pycon-1.0.1.dist-info/entry_points.txt
markdown_pycon-1.0.1.dist-info/licenses/LICENSE
markdown_pycon/__init__.py
markdown_pycon/_extension.py
markdown_pycon/debug.py
markdown_pycon/py.typed
markdown_pycon-1.0.1.dist-info/RECORD
