Metadata-Version: 2.1
Name: markdown-pycon
Version: 1.0.1
Summary: Markdown extension to parse `pycon` code blocks without indentation or fences.
Author-Email: =?utf-8?q?Timoth=C3=A9e_Mazzucotelli?= <dev@pawamoy.fr>
License: ISC
Classifier: Development Status :: 4 - Beta
Classifier: Intended Audience :: Developers
Classifier: Programming Language :: Python
Classifier: Programming Language :: Python :: 3
Classifier: Programming Language :: Python :: 3 :: Only
Classifier: Programming Language :: Python :: 3.9
Classifier: Programming Language :: Python :: 3.10
Classifier: Programming Language :: Python :: 3.11
Classifier: Programming Language :: Python :: 3.12
Classifier: Programming Language :: Python :: 3.13
Classifier: Programming Language :: Python :: 3.14
Classifier: Topic :: Documentation
Classifier: Topic :: Software Development
Classifier: Topic :: Utilities
Classifier: Typing :: Typed
Project-URL: Homepage, https://pawamoy.github.io/markdown-pycon
Project-URL: Documentation, https://pawamoy.github.io/markdown-pycon
Project-URL: Changelog, https://pawamoy.github.io/markdown-pycon/changelog
Project-URL: Repository, https://github.com/pawamoy/markdown-pycon
Project-URL: Issues, https://github.com/pawamoy/markdown-pycon/issues
Project-URL: Discussions, https://github.com/pawamoy/markdown-pycon/discussions
Project-URL: Gitter, https://gitter.im/markdown-pycon/community
Project-URL: Funding, https://github.com/sponsors/pawamoy
Requires-Python: >=3.9
